gitlabtree/__init__.py
gitlabtree/__main__.py
gitlabtree/gitlab_helper.py
gitlabtree/main.py
gitlabtree/models.py
gitlabtree/permissions.py
gitlabtree/pipeline.py
gitlabtree/rich_helper.py
gitlabtree/runner.py
gitlabtree/tree_helper.py
gitlabtree/visibility.py
gitlabtree-0.1.2.dist-info/entry_points.txt
gitlabtree-0.1.2.dist-info/WHEEL
gitlabtree-0.1.2.dist-info/METADATA
gitlabtree-0.1.2.dist-info/RECORD
