Metadata-Version: 2.1
Name: gitlabtree
Version: 0.1.2
Summary: CLI tool for gathering GitLab information in tree format
Author: ubaumann
Author-email: github@m.ubaumann.ch
Requires-Python: >=3.8,<4.0
Classifier: Programming Language :: Python :: 3
Classifier: Programming Language :: Python :: 3.10
Classifier: Programming Language :: Python :: 3.8
Classifier: Programming Language :: Python :: 3.9
Requires-Dist: pydantic (>=1,<2)
Requires-Dist: requests (>=2,<3)
Requires-Dist: rich (>=12,<13)
Requires-Dist: typer (>=0.6,<0.7)
Requires-Dist: types-requests (>=2,<3)
